monolens/README.md
monolens/__init__.py
monolens/__main__.py
monolens/_version.py
monolens/lens.py
monolens/util.py
monolens-0.7.2.dist-info/LICENSE
monolens-0.7.2.dist-info/METADATA
monolens-0.7.2.dist-info/WHEEL
monolens-0.7.2.dist-info/entry_points.txt
monolens-0.7.2.dist-info/top_level.txt
monolens-0.7.2.dist-info/RECORD
