Metadata-Version: 2.1
Name: monolens
Version: 0.7.2
Summary: View part of your screen in monochrome colors or in simulated protanopia, deuteranopia, or tritanopia
Home-page: https://github.com/hdembinski/monolens
Author: Hans Dembinski
Author-email: hans.dembinski@gmail.com
License: MIT
Project-URL: Bug Tracker, https://github.com/hdembinski/monolens/issues
Platform: UNKNOWN
Classifier: Programming Language :: Python :: 3
Classifier: License :: OSI Approved :: MIT License
Classifier: Operating System :: OS Independent
Requires-Python: >=3.6
Requires-Dist: pyside6
Requires-Dist: numpy
Requires-Dist: numba
Requires-Dist: importlib-resources ; python_version < "3.9"
